badwords.py
badwords-1.2.4.0.dist-info/METADATA
badwords-1.2.4.0.dist-info/WHEEL
badwords-1.2.4.0.dist-info/top_level.txt
badwords-1.2.4.0.dist-info/RECORD
