Metadata-Version: 2.1
Name: badwords
Version: 1.2.4.0
Summary: a small pkg demos for you and everyone
Home-page: UNKNOWN
License: UNKNOWN
Platform: UNKNOWN
